meshagent/anthropic/__init__.py
meshagent/anthropic/mcp.py
meshagent/anthropic/messages_adapter.py
meshagent/anthropic/openai_responses_stream_adapter.py
meshagent/anthropic/request_tool.py
meshagent/anthropic/version.py
meshagent/anthropic/web_fetch.py
meshagent/anthropic/web_search.py
meshagent/anthropic/proxy/__init__.py
meshagent/anthropic/proxy/proxy.py
meshagent/anthropic/tests/anthropic_live_test.py
meshagent/anthropic/tests/mcp_test.py
meshagent/anthropic/tests/messages_adapter_test.py
meshagent/anthropic/tests/openai_responses_stream_adapter_test.py
meshagent_anthropic-0.25.1.dist-info/licenses/LICENSE
meshagent_anthropic-0.25.1.dist-info/METADATA
meshagent_anthropic-0.25.1.dist-info/WHEEL
meshagent_anthropic-0.25.1.dist-info/top_level.txt
meshagent_anthropic-0.25.1.dist-info/RECORD
